{"id":"kokosove-mlieko","nazov":"kokosové mlieko","kategoria":"Základy a koreniny","jednotka":"ml","trvanlivost":"trvanlive","gramy_za_ks":null,"spotreba_dni":null,"alergeny":[],"sezona":null,"bezna_cena":2.2,"bezne_balenie":"400 ml","ceny":[{"obchod":"Terno","nazov_v_letaku":"Asia Time kokosové mlieko","mnozstvo":"400 ml (1 l = 4,23)","balenie_qty":400.0,"balenie_jednotka":"ml","povodna_cena":null,"zlavnena_cena":1.69,"zlava":"VÝHODNÁ CENA","platnost_od":"2026-07-16","platnost_do":"2026-07-22","podmienka":"VÝHODNÁ CENA","kategoria_letak":"Trvanlivé a základ","nazov_norm":"asia time kokosove mlieko","jednotkova_cena":0.00422}],"statistiky":{"bezna_jednotkova_cena":0.00422,"min_jednotkova_cena":0.00422,"pocet_zaznamov":1},"aktualne_najlacnejsie":{"obchod":"Terno","nazov_v_letaku":"Asia Time kokosové mlieko","zlavnena_cena":1.69,"mnozstvo":"400 ml (1 l = 4,23)","jednotkova_cena":0.00422,"zlava":"VÝHODNÁ CENA","podmienka":"VÝHODNÁ CENA","platnost_do":"2026-07-22"}}